<?xml version="1.0" encoding="UTF-8"?>
<!DOCTYPE plist
PUBLIC "-//Apple//DTD PLIST 1.0//EN"
       "http://www.apple.com/DTDs/PropertyList-1.0.dtd">
<plist version="1.0">
 <dict>
  <key>items</key>
  <array>
   <dict>
    <key>assets</key>
    <array>
     <dict>
      <key>kind</key>
      <string>software-package</string>
      <key>url</key>
      <string>http://lovemetoyou.qiniudn.com/o_1au7an56p1r089235r91da11f2m9.ipa</string>
     </dict>
     <dict>
      <key>kind</key>
      <string>display-image</string>
      <key>needs-shine</key>
      <true/>
      <key>url</key>
      <string>http://www.thisding.com/wechat/Icon.png</string>
     </dict>
     <dict>
      <key>kind</key>
      <string>full-size-image</string>
      <key>needs-shine</key>
      <true/>
      <key>url</key>
      <string>http://www.thisding.com/wechat/Icon.png</string>
     </dict>
    </array>
    <key>metadata</key>
    <dict>
     <key>bundle-identifier</key>
     <string>com.asiainfo.LetterPlus</string>
     <key>bundle-version</key>
     <string>6.3.25</string>
     <key>kind</key>
     <string>software</string>
     <key>subtitle</key>
     <string>com.asiainfo.LetterPlus</string>
     <key>title</key>
     <string>牛逼1.0</string>
    </dict>
   </dict>
  </array>
 </dict>
</plist>
